setup.py
Tamia.egg-info/PKG-INFO
Tamia.egg-info/SOURCES.txt
Tamia.egg-info/dependency_links.txt
Tamia.egg-info/requires.txt
Tamia.egg-info/top_level.txt
tamia/__init__.py
tamia/api.py
tamia/errors.py
tamia/index.py
tamia/utils.py
tamia/version.py
test/test_repository.py