Metadata-Version: 1.0
Name: Tamia
Version: 0.1.3
Summary: A wrapper for pygit2
Home-page: https://github.com/olivier-m/Tamia
Author: Olivier Meunier
Author-email: olivier@neokraft.net
License: MIT License
Keywords: g,i,t, ,v,c,s, ,l,i,b,g,i,t,2
Platform: UNKNOWN
Classifier: Development Status :: 4 - Beta
Classifier: Intended Audience :: Developers
Classifier: License :: OSI Approved :: MIT License
Classifier: Operating System :: OS Independent
Classifier: Programming Language :: Python :: 2.6
Classifier: Programming Language :: Python :: 2.7
Classifier: Topic :: Software Development :: Libraries
Classifier: Topic :: Utilities
